wappdriver/__init__.py
wappdriver/cli.py
wappdriver/driver.py
wappdriver/error.py
wappdriver/local.py
wappdriver/whatsapp.py
wappdriver-0.6.6.dist-info/LICENSE
wappdriver-0.6.6.dist-info/METADATA
wappdriver-0.6.6.dist-info/WHEEL
wappdriver-0.6.6.dist-info/entry_points.txt
wappdriver-0.6.6.dist-info/top_level.txt
wappdriver-0.6.6.dist-info/RECORD
