Metadata-Version: 2.1
Name: wappdriver
Version: 0.6.6
Summary: A package that automates sending messages through WhatsApp Web 
Home-page: https://github.com/aahnik/wappdriver
Author: Aahnik Daw
Author-email: meet.aahnik@gmail.com
License: MIT
Platform: UNKNOWN
Classifier: Programming Language :: Python :: 3
Classifier: License :: OSI Approved :: MIT License
Classifier: Operating System :: OS Independent
Requires-Python: >=3.8
